sphinx_to_sqlite/__init__.py
sphinx_to_sqlite/cli.py
sphinx_to_sqlite-0.1a1.dist-info/LICENSE
sphinx_to_sqlite-0.1a1.dist-info/METADATA
sphinx_to_sqlite-0.1a1.dist-info/WHEEL
sphinx_to_sqlite-0.1a1.dist-info/entry_points.txt
sphinx_to_sqlite-0.1a1.dist-info/top_level.txt
sphinx_to_sqlite-0.1a1.dist-info/RECORD
