Metadata-Version: 2.1
Name: sphinx-to-sqlite
Version: 0.1a1
Summary: Create a SQLite database from Sphinx documentation
Home-page: https://github.com/simonw/sphinx-to-sqlite
Author: Simon Willison
License: Apache License, Version 2.0
Project-URL: Issues, https://github.com/simonw/sphinx-to-sqlite/issues
Project-URL: CI, https://github.com/simonw/sphinx-to-sqlite/actions
Project-URL: Changelog, https://github.com/simonw/sphinx-to-sqlite/releases
Platform: UNKNOWN
Requires-Dist: click
Requires-Dist: sqlite-utils
Provides-Extra: test
Requires-Dist: pytest ; extra == 'test'
